LICENSE
MANIFEST.in
README.md
requirements.txt
setup.cfg
setup.py
hydromap/__init__.py
hydromap/common.py
hydromap/hydromap.py
hydromap.egg-info/PKG-INFO
hydromap.egg-info/SOURCES.txt
hydromap.egg-info/dependency_links.txt
hydromap.egg-info/not-zip-safe
hydromap.egg-info/top_level.txt
tests/test_hydromap.py