Metadata-Version: 2.1
Name: hydromap
Version: 0.0.1
Summary: A python package for hydrological analysis interactive mapping.
Home-page: https://github.com/aSalih1/hydromap
Author: Abdelrahim Salih
Author-email: rahim.salih33@gmail.com
License: MIT license
Keywords: hydromap
Classifier: Intended Audience :: Developers
Classifier: License :: OSI Approved :: MIT License
Classifier: Natural Language :: English
Classifier: Programming Language :: Python :: 3
Classifier: Programming Language :: Python :: 3.8
Classifier: Programming Language :: Python :: 3.9
Classifier: Programming Language :: Python :: 3.10
Classifier: Programming Language :: Python :: 3.11
Requires-Python: >=3.8
License-File: LICENSE
